fastgtp/__init__.py
fastgtp/server/__init__.py
fastgtp/server/gtp.py
fastgtp/server/main.py
fastgtp/server/router.py
fastgtp/server/transport.py
fastgtp-0.0.1.dist-info/METADATA
fastgtp-0.0.1.dist-info/WHEEL
fastgtp-0.0.1.dist-info/licenses/LICENSE
fastgtp-0.0.1.dist-info/RECORD
