Metadata-Version: 2.4
Name: fastgtp
Version: 0.0.1
Summary: A FastAPI wrapper that turns Go Text Protocol engines into REST APIs.
License: PolyForm-Noncommercial-1.0.0
License-File: LICENSE
Author: ReiRev
Author-email: reirev2913@gmail.com
Requires-Python: >=3.10
Classifier: License :: Other/Proprietary License
Classifier: Programming Language :: Python :: 3
Classifier: Programming Language :: Python :: 3.10
Classifier: Programming Language :: Python :: 3.11
Classifier: Programming Language :: Python :: 3.12
Classifier: Programming Language :: Python :: 3.13
Classifier: Programming Language :: Python :: 3.14
Requires-Dist: fastapi (>=0.118.0,<0.119.0)
Requires-Dist: uvicorn[standard] (>=0.31.0,<0.32.0)
